ignore4/__init__.py
ignore4/main.py
ignore4-1.0.0.dist-info/LICENSE
ignore4-1.0.0.dist-info/METADATA
ignore4-1.0.0.dist-info/WHEEL
ignore4-1.0.0.dist-info/entry_points.txt
ignore4-1.0.0.dist-info/top_level.txt
ignore4-1.0.0.dist-info/RECORD
