Metadata-Version: 2.1
Name: ignore4
Version: 1.0.0
Summary: A wrapper script for downloading gitignore files from github/gitignore
Home-page: https://github.com/Smeb/ignore4
Author: Ben Ryves
Author-email: bryves@gmail.com
License: MIT
Platform: UNKNOWN
